README.md
setup.py
QuickMath/__init__.py
QuickMath/icon.icns
QuickMath/icon.ico
QuickMath/sponsor.jpg
QuickMath/style.css
QuickMath/test.py
QuickMath.egg-info/PKG-INFO
QuickMath.egg-info/SOURCES.txt
QuickMath.egg-info/dependency_links.txt
QuickMath.egg-info/entry_points.txt
QuickMath.egg-info/requires.txt
QuickMath.egg-info/top_level.txt
QuickMath/misc/README_zh.html
QuickMath/misc/assets/icon.ico
QuickMath/misc/assets/image-20200904070647991.png
QuickMath/misc/assets/image-20200904075335241.png
QuickMath/misc/assets/sponsor.jpg
QuickMath/moduels/ConfigTab.py
QuickMath/moduels/HelpTab.py
QuickMath/moduels/LatexLiveAPI.py
QuickMath/moduels/LatexLiveTab.py
QuickMath/moduels/MathpixAPI.py
QuickMath/moduels/QuickMathTab.py
QuickMath/moduels/ResultLogTab.py
QuickMath/moduels/SponsorDialog.py
QuickMath/moduels/SystemTray.py
QuickMath/misc/README_zh.html
QuickMath/misc/assets/icon.ico
QuickMath/misc/assets/image-20200904070647991.png
QuickMath/misc/assets/image-20200904075335241.png
QuickMath/misc/assets/sponsor.jpg
QuickMath/moduels/ConfigTab.py
QuickMath/moduels/HelpTab.py
QuickMath/moduels/LatexLiveAPI.py
QuickMath/moduels/LatexLiveTab.py
QuickMath/moduels/MathpixAPI.py
QuickMath/moduels/QuickMathTab.py
QuickMath/moduels/ResultLogTab.py
QuickMath/moduels/SponsorDialog.py
QuickMath/moduels/SystemTray.py