Metadata-Version: 2.1
Name: QuickMath
Version: 1.5.0
Summary: 快速的数学公式手写插入工具（使用了 Mathpix API）
Home-page: https://github.com/HaujetZhao/QuickMath
Author: Haujet Zhao
Author-email: 1292756898@qq.com
Maintainer: Haujet Zhao
Maintainer-email: 1292756898@qq.com
License: MPL-2.0 License
Platform: all
Classifier: Development Status :: 4 - Beta
Classifier: Intended Audience :: End Users/Desktop
Classifier: Topic :: Multimedia :: Video
Classifier: License :: OSI Approved :: Mozilla Public License 2.0 (MPL 2.0)
Classifier: Programming Language :: Python :: 3
Classifier: Programming Language :: Python :: 3.5
Classifier: Programming Language :: Python :: 3.6
Classifier: Programming Language :: Python :: 3.7
Classifier: Programming Language :: Python :: 3.8
Classifier: Programming Language :: Python :: 3 :: Only
Requires-Python: >=3.5, <4
